setup.cfg
setup.py
artikcloud/__init__.py
artikcloud/api_client.py
artikcloud/configuration.py
artikcloud/rest.py
artikcloud.egg-info/PKG-INFO
artikcloud.egg-info/SOURCES.txt
artikcloud.egg-info/dependency_links.txt
artikcloud.egg-info/requires.txt
artikcloud.egg-info/top_level.txt
artikcloud/apis/__init__.py
artikcloud/apis/device_types_api.py
artikcloud/apis/devices_api.py
artikcloud/apis/devices_management_api.py
artikcloud/apis/devices_shares_api.py
artikcloud/apis/devices_status_api.py
artikcloud/apis/export_api.py
artikcloud/apis/messages_api.py
artikcloud/apis/monetization_api.py
artikcloud/apis/registrations_api.py
artikcloud/apis/rules_api.py
artikcloud/apis/subscriptions_api.py
artikcloud/apis/tags_api.py
artikcloud/apis/tokens_api.py
artikcloud/apis/users_api.py
artikcloud/apis/whitelisting_api.py
artikcloud/models/__init__.py
artikcloud/models/ack_envelope.py
artikcloud/models/acknowledgement.py
artikcloud/models/action.py
artikcloud/models/action_array.py
artikcloud/models/action_details.py
artikcloud/models/action_details_array.py
artikcloud/models/action_in.py
artikcloud/models/action_out.py
artikcloud/models/actions.py
artikcloud/models/aggregate_data.py
artikcloud/models/aggregates_histogram_data.py
artikcloud/models/aggregates_histogram_response.py
artikcloud/models/aggregates_response.py
artikcloud/models/app_properties.py
artikcloud/models/certificate_data.py
artikcloud/models/certificate_envelope.py
artikcloud/models/certificate_fields.py
artikcloud/models/certificate_id.py
artikcloud/models/check_token_message.py
artikcloud/models/check_token_response.py
artikcloud/models/contact_info.py
artikcloud/models/device.py
artikcloud/models/device_array.py
artikcloud/models/device_envelope.py
artikcloud/models/device_pricing_tier.py
artikcloud/models/device_pricing_tier_envelope.py
artikcloud/models/device_pricing_tier_request.py
artikcloud/models/device_pricing_tiers.py
artikcloud/models/device_pricing_tiers_envelope.py
artikcloud/models/device_reg_complete_request.py
artikcloud/models/device_reg_confirm_user_request.py
artikcloud/models/device_reg_confirm_user_response.py
