Metadata-Version: 1.0
Name: artikcloud
Version: 2.2.2
Summary: ARTIK Cloud API
Home-page: UNKNOWN
Author: UNKNOWN
Author-email: UNKNOWN
License: UNKNOWN
Keywords: ARTIK Cloud API
Platform: UNKNOWN
